{"nodes": [{"id": "d_work_modulecodeit_eridanus_opencart_system_library_cache_mem_php", "label": "mem.php", "file_type": "code", "source_file": "system/library/cache/mem.php", "source_location": "L1"}, {"id": "cache_mem_mem", "label": "Mem", "file_type": "code", "source_file": "system/library/cache/mem.php", "source_location": "L3"}, {"id": "cache_mem_mem_construct", "label": ".__construct()", "file_type": "code", "source_file": "system/library/cache/mem.php", "source_location": "L9"}, {"id": "cache_mem_mem_get", "label": ".get()", "file_type": "code", "source_file": "system/library/cache/mem.php", "source_location": "L16"}, {"id": "cache_mem_mem_set", "label": ".set()", "file_type": "code", "source_file": "system/library/cache/mem.php", "source_location": "L20"}, {"id": "cache_mem_mem_delete", "label": ".delete()", "file_type": "code", "source_file": "system/library/cache/mem.php", "source_location": "L24"}], "edges": [{"source": "d_work_modulecodeit_eridanus_opencart_system_library_cache_mem_php", "target": "cache_mem_mem", "relation": "contains", "confidence": "EXTRACTED", "source_file": "system/library/cache/mem.php", "source_location": "L3", "weight": 1.0}, {"source": "cache_mem_mem", "target": "cache_mem_mem_construct", "relation": "method", "confidence": "EXTRACTED", "source_file": "system/library/cache/mem.php", "source_location": "L9", "weight": 1.0}, {"source": "cache_mem_mem", "target": "cache_mem_mem_get", "relation": "method", "confidence": "EXTRACTED", "source_file": "system/library/cache/mem.php", "source_location": "L16", "weight": 1.0}, {"source": "cache_mem_mem", "target": "cache_mem_mem_set", "relation": "method", "confidence": "EXTRACTED", "source_file": "system/library/cache/mem.php", "source_location": "L20", "weight": 1.0}, {"source": "cache_mem_mem", "target": "cache_mem_mem_delete", "relation": "method", "confidence": "EXTRACTED", "source_file": "system/library/cache/mem.php", "source_location": "L24", "weight": 1.0}], "raw_calls": [{"caller_nid": "cache_mem_mem_construct", "callee": "pconnect", "is_member_call": true, "source_file": "D:\\work\\modulecodeit\\eridanus-opencart\\system\\library\\cache\\mem.php", "source_location": "L13", "receiver": null}]}