{"nodes": [{"id": "d_work_modulecodeit_eridanus_opencart_admin_controller_common_logout_php", "label": "logout.php", "file_type": "code", "source_file": "admin/controller/common/logout.php", "source_location": "L1"}, {"id": "common_logout_controllercommonlogout", "label": "ControllerCommonLogout", "file_type": "code", "source_file": "admin/controller/common/logout.php", "source_location": "L2"}, {"id": "controller", "label": "Controller", "file_type": "code", "source_file": "", "source_location": ""}, {"id": "common_logout_controllercommonlogout_index", "label": ".index()", "file_type": "code", "source_file": "admin/controller/common/logout.php", "source_location": "L3"}], "edges": [{"source": "d_work_modulecodeit_eridanus_opencart_admin_controller_common_logout_php", "target": "common_logout_controllercommonlogout", "relation": "contains", "confidence": "EXTRACTED", "source_file": "admin/controller/common/logout.php", "source_location": "L2", "weight": 1.0}, {"source": "common_logout_controllercommonlogout", "target": "controller", "relation": "inherits", "confidence": "EXTRACTED", "source_file": "admin/controller/common/logout.php", "source_location": "L2", "weight": 1.0}, {"source": "common_logout_controllercommonlogout", "target": "common_logout_controllercommonlogout_index", "relation": "method", "confidence": "EXTRACTED", "source_file": "admin/controller/common/logout.php", "source_location": "L3", "weight": 1.0}], "raw_calls": [{"caller_nid": "common_logout_controllercommonlogout_index", "callee": "logout", "is_member_call": true, "source_file": "D:\\work\\modulecodeit\\eridanus-opencart\\admin\\controller\\common\\logout.php", "source_location": "L4", "receiver": null}, {"caller_nid": "common_logout_controllercommonlogout_index", "callee": "redirect", "is_member_call": true, "source_file": "D:\\work\\modulecodeit\\eridanus-opencart\\admin\\controller\\common\\logout.php", "source_location": "L8", "receiver": null}, {"caller_nid": "common_logout_controllercommonlogout_index", "callee": "link", "is_member_call": true, "source_file": "D:\\work\\modulecodeit\\eridanus-opencart\\admin\\controller\\common\\logout.php", "source_location": "L8", "receiver": null}]}